MANIFEST.in
Makefile
README.md
setup.py
calysto_prolog/__init__.py
calysto_prolog/__main__.py
calysto_prolog/kernel.py
calysto_prolog/prolog.py
calysto_prolog.egg-info/PKG-INFO
calysto_prolog.egg-info/SOURCES.txt
calysto_prolog.egg-info/dependency_links.txt
calysto_prolog.egg-info/requires.txt
calysto_prolog.egg-info/top_level.txt
calysto_prolog/images/logo-32x32.png
calysto_prolog/images/logo-64x64.png