Metadata-Version: 1.1
Name: calysto-prolog
Version: 0.8.4
Summary: A Prolog kernel for Jupyter that can use Python libraries
Home-page: https://github.com/Calysto/calysto_prolog
Author: Douglas Blank
Author-email: doug.blank@gmail.com
License: UNKNOWN
Platform: UNKNOWN
Classifier: Framework :: IPython
Classifier: License :: OSI Approved :: BSD License
Classifier: Programming Language :: Python :: 3
Classifier: Programming Language :: Python :: 2
